pastime/__init__.py
pastime/formatter.py
pastimepy-0.1.0.dist-info/licenses/LICENSE
pastimepy-0.1.0.dist-info/METADATA
pastimepy-0.1.0.dist-info/WHEEL
pastimepy-0.1.0.dist-info/top_level.txt
pastimepy-0.1.0.dist-info/RECORD
