Metadata-Version: 2.4
Name: pastimepy
Version: 0.1.0
Summary: Human-readable datetime formatter
Author: Gagan
Author-email: gagan.globin76@gmail.com
License: MIT
Classifier: Programming Language :: Python :: 3
Classifier: License :: OSI Approved :: MIT License
Classifier: Operating System :: OS Independent
Requires-Python: >=3.6
License-File: LICENSE
Dynamic: author
Dynamic: author-email
Dynamic: classifier
Dynamic: license
Dynamic: license-file
Dynamic: requires-python
Dynamic: summary
